proto_explorer/__init__.py
proto_explorer/proto_explorer.py
proto_explorer-0.3.7.dist-info/LICENSE
proto_explorer-0.3.7.dist-info/METADATA
proto_explorer-0.3.7.dist-info/WHEEL
proto_explorer-0.3.7.dist-info/entry_points.txt
proto_explorer-0.3.7.dist-info/RECORD
