Metadata-Version: 2.3
Name: proto-explorer
Version: 0.3.7
Summary: A tool to visualize .proto file hierarchies
License: MIT
Keywords: protobuf,grpc,schema,explorer,streamlit
Author: Lei Yuan
Author-email: lee14159@gmail.com
Requires-Python: >=3.10
Classifier: License :: OSI Approved :: MIT License
Classifier: Programming Language :: Python :: 3
Classifier: Programming Language :: Python :: 3.10
Classifier: Programming Language :: Python :: 3.11
Classifier: Programming Language :: Python :: 3.12
Classifier: Programming Language :: Python :: 3.13
Requires-Dist: grpcio-tools (>=1.75.0)
Requires-Dist: protobuf (>=6.31.0,<7.0.0)
Requires-Dist: requests (>=2.0.0)
Requires-Dist: streamlit (>=1.50.0,<2.0.0)
